gitrics/__init__.py
gitrics/configuration.py
gitrics/user.py
gitrics/utilities.py
gitrics/cli/__init__.py
gitrics/cli/gitrics.py
gitrics/project/__init__.py
gitrics/project/enrichment.py
gitrics-0.7.2.dist-info/METADATA
gitrics-0.7.2.dist-info/WHEEL
gitrics-0.7.2.dist-info/entry_points.txt
gitrics-0.7.2.dist-info/top_level.txt
gitrics-0.7.2.dist-info/RECORD
