Metadata-Version: 2.1
Name: gitrics
Version: 0.7.2
Summary: Python package to generate metrics based off git usage.
Home-page: https://gitlab.com/lgensinger/gitrics
Requires-Dist: colorgram.py
Requires-Dist: colorama
Requires-Dist: glapi (>=0.7.3)
Requires-Dist: networkx
Requires-Dist: scipy
Provides-Extra: test
Requires-Dist: lorem ; extra == 'test'
Requires-Dist: pkgparser ; extra == 'test'
Requires-Dist: pytest ; extra == 'test'
Requires-Dist: pytest-cov ; extra == 'test'
